wcp_library/__init__.py
wcp_library/browser_automation/__init__.py
wcp_library/browser_automation/browser.py
wcp_library/browser_automation/interactions.py
wcp_library/credentials/__init__.py
wcp_library/credentials/_credential_manager_asynchronous.py
wcp_library/credentials/_credential_manager_synchronous.py
wcp_library/credentials/api.py
wcp_library/credentials/ftp.py
wcp_library/credentials/internet.py
wcp_library/credentials/oracle.py
wcp_library/credentials/postgres.py
wcp_library/emailing.py
wcp_library/ftp/__init__.py
wcp_library/ftp/ftp.py
wcp_library/ftp/sftp.py
wcp_library/graph/__init__.py
wcp_library/graph/mail.py
wcp_library/graph/sharepoint.py
wcp_library/graph/subscription.py
wcp_library/informatica.py
wcp_library/logging.py
wcp_library/selenium/__init__.py
wcp_library/selenium/_selenium_driver.py
wcp_library/selenium/selenium_helper.py
wcp_library/sql/__init__.py
wcp_library/sql/oracle.py
wcp_library/sql/postgres.py
wcp_library/time.py
wcp_library-1.8.4.dist-info/METADATA
wcp_library-1.8.4.dist-info/WHEEL
wcp_library-1.8.4.dist-info/RECORD
